qiuwenbot/__init__.py
qiuwenbot/__main__.py
qiuwenbot/argparse.py
qiuwenbot/bot.py
qiuwenbot/qwfamily.py
qiuwenbot/qwlogger.py
qiuwenbot/user-config.py
qiuwenbot/utils.py
qiuwenbot/entrypoints/__init__.py
qiuwenbot/entrypoints/submit.py
qiuwenbot/filter/__init__.py
qiuwenbot/filter/clean_refs.py
qiuwenbot/filter/common.py
qiuwenbot/filter/deprecated_tags.py
qiuwenbot/filter/expired_templates.py
qiuwenbot/filter/filter.py
qiuwenbot/filter/gov.py
qiuwenbot/filter/history.py
qiuwenbot/filter/hk.py
qiuwenbot/filter/ref_blacklist.txt
qiuwenbot/filter/roc_flag.py
qiuwenbot/filter/roc_year.py
qiuwenbot/filter/tw.py
qiuwenbot/filter/wg.py
qiuwenbot/task/__init__.py
qiuwenbot/task/duplicate.py
qiuwenbot/task/filter.py
qiuwenbot/task/task.py
qiuwenbot-0.0.2.dist-info/LICENSE
qiuwenbot-0.0.2.dist-info/METADATA
qiuwenbot-0.0.2.dist-info/WHEEL
qiuwenbot-0.0.2.dist-info/entry_points.txt
qiuwenbot-0.0.2.dist-info/top_level.txt
qiuwenbot-0.0.2.dist-info/RECORD
