Metadata-Version: 2.1
Name: qiuwenbot
Version: 0.0.2
Summary: Qiuwen Baike bot/求闻百科机器人
Author-email: Jinzhe Zeng <jinzhe.zeng@rutgers.edu>
License: GNU GENERAL PUBLIC LICENSE
Project-URL: repository, https://github.com/njzjz/qiuwenbot
Keywords: qiuwen,bot
Classifier: Programming Language :: Python
Classifier: Programming Language :: Python :: 3
Classifier: Natural Language :: English
Requires-Python: >=3.7
License-File: LICENSE
Requires-Dist: pywikibot (>=8)
Requires-Dist: requests
Requires-Dist: zhconv
Requires-Dist: cn2an
Requires-Dist: tqdm
Requires-Dist: dargs
Provides-Extra: docs
Requires-Dist: sphinx ; extra == 'docs'
Requires-Dist: myst-parser ; extra == 'docs'
Requires-Dist: furo ; extra == 'docs'
Requires-Dist: numpydoc ; extra == 'docs'
Requires-Dist: dargs (>=0.3.1) ; extra == 'docs'
Requires-Dist: sphinx-argparse ; extra == 'docs'
Provides-Extra: test
Requires-Dist: pytest ; extra == 'test'
Requires-Dist: pytest-cov ; extra == 'test'
